<?xml version="1.0" encoding="utf-8"?>
<odoo>
     <record id="paperformat_euro_lowmargin" model="report.paperformat">
        <field name="name">European A4 low margin</field>
        <field name="default" eval="True"/>
        <field name="format">A4</field>
        <field name="page_height">0</field>
        <field name="page_width">0</field>
        <field name="orientation">Portrait</field>
        <field name="margin_top">5</field>
        <field name="margin_bottom">5</field>
        <field name="margin_left">5</field>
        <field name="margin_right">5</field>
        <field name="header_line" eval="False"/>
        <field name="header_spacing">0</field>
        <field name="dpi">80</field>
    </record>

    <record id="rental_property_details_report" model="ir.actions.report">
        <field name="name">Rental Reports</field>
        <field name="model">property.details</field>
        <field name="report_type">qweb-pdf</field>
        <field name="report_name">property_rental.rental_property_report</field>
        <field name="report_file">property_rental.rental_property_report</field>
        <field name="print_report_name">'Rental Property - %s' % (object.property_name or 'Attendee').replace('/','')</field>
        <field name="paperformat_id" ref="estate.paperformat_euro_lowmargin"/>
        <field name="binding_model_id" ref="model_property_details"/>
        <field name="binding_type">report</field>
    </record>

    <record id="tenant_owned_property_report" model="ir.actions.report">
        <field name="name">Rented Property</field>
        <field name="model">res.users</field>
        <field name="report_type">qweb-pdf</field>
        <field name="report_name">property_rental.owned_property_report</field>
        <field name="report_file">property_rental.owned_property_report</field>
        <field name="print_report_name">'Rental Property - %s' % (object.name or 'Attendee').replace('/','')</field>
        <field name="paperformat_id" ref="estate.paperformat_euro_lowmargin"/>
        <field name="binding_model_id" ref="model_res_users"/>
        <field name="binding_type">report</field>
    </record>

</odoo>